nbdev_demo/__init__.py
nbdev_demo/_nbdev.py
nbdev_demo/card.py
nbdev_demo/core.py
nbdev_demo/deck.py
nbdev_demo-0.0.1.dist-info/LICENSE
nbdev_demo-0.0.1.dist-info/METADATA
nbdev_demo-0.0.1.dist-info/WHEEL
nbdev_demo-0.0.1.dist-info/entry_points.txt
nbdev_demo-0.0.1.dist-info/top_level.txt
nbdev_demo-0.0.1.dist-info/RECORD
